publiplots/__init__.py
publiplots/fonts/Arial_Black.ttf
publiplots/fonts/Arial_Bold.ttf
publiplots/fonts/Arial_Bold_Italic.ttf
publiplots/fonts/Arial_Italic.ttf
publiplots/plot/__init__.py
publiplots/plot/bar.py
publiplots/plot/box.py
publiplots/plot/point.py
publiplots/plot/raincloud.py
publiplots/plot/scatter.py
publiplots/plot/strip.py
publiplots/plot/swarm.py
publiplots/plot/violin.py
publiplots/plot/upset/__init__.py
publiplots/plot/upset/diagram.py
publiplots/plot/upset/draw.py
publiplots/plot/upset/logic.py
publiplots/plot/venn/__init__.py
publiplots/plot/venn/diagram.py
publiplots/plot/venn/draw.py
publiplots/plot/venn/geometry.py
publiplots/plot/venn/logic.py
publiplots/themes/__init__.py
publiplots/themes/colors.py
publiplots/themes/hatches.py
publiplots/themes/linestyles.py
publiplots/themes/markers.py
publiplots/themes/rcparams.py
publiplots/themes/styles.py
publiplots/utils/__init__.py
publiplots/utils/axes.py
publiplots/utils/fonts.py
publiplots/utils/io.py
publiplots/utils/legend.py
publiplots/utils/offset.py
publiplots/utils/transparency.py
publiplots/utils/validation.py
publiplots-0.4.6.dist-info/METADATA
publiplots-0.4.6.dist-info/WHEEL
publiplots-0.4.6.dist-info/licenses/LICENSE
publiplots-0.4.6.dist-info/RECORD
