Metadata-Version: 2.4
Name: publiplots
Version: 0.4.6
Summary: Publication-ready plotting with a clean, modular API
Project-URL: Homepage, https://github.com/jorgebotas/publiplots
Project-URL: Documentation, https://github.com/jorgebotas/publiplots
Project-URL: Repository, https://github.com/jorgebotas/publiplots
Project-URL: Issues, https://github.com/jorgebotas/publiplots/issues
Author-email: Jorge Botas <jorgebotas.github@gmail.com>
License: MIT
License-File: LICENSE
Keywords: bubbleplot,heatmap,matplotlib,plotting,publication,seaborn,venn,visualization
Classifier: Development Status :: 4 - Beta
Classifier: Intended Audience :: Science/Research
Classifier: License :: OSI Approved :: MIT License
Classifier: Programming Language :: Python :: 3
Classifier: Programming Language :: Python :: 3.9
Classifier: Programming Language :: Python :: 3.10
Classifier: Programming Language :: Python :: 3.11
Classifier: Programming Language :: Python :: 3.12
Classifier: Topic :: Scientific/Engineering :: Visualization
Requires-Python: >=3.9
Requires-Dist: matplotlib>=3.7.0
Requires-Dist: numpy>=1.21.0
Requires-Dist: pandas>=1.3.0
Requires-Dist: seaborn>=0.12.0
Provides-Extra: dev
Requires-Dist: black>=23.0.0; extra == 'dev'
Requires-Dist: mypy>=1.0.0; extra == 'dev'
Requires-Dist: pytest-cov>=4.0.0; extra == 'dev'
Requires-Dist: pytest>=7.0.0; extra == 'dev'
Requires-Dist: ruff>=0.1.0; extra == 'dev'
Provides-Extra: docs
Requires-Dist: numpydoc>=1.6.0; extra == 'docs'
Requires-Dist: pillow>=10.0.0; extra == 'docs'
Requires-Dist: shibuya>=2024.0.0; extra == 'docs'
Requires-Dist: sphinx-gallery>=0.15.0; extra == 'docs'
Requires-Dist: sphinx>=7.0.0; extra == 'docs'
